nonebot_plugin_tortoise_orm-0.1.4.dist-info/METADATA
nonebot_plugin_tortoise_orm-0.1.4.dist-info/WHEEL
nonebot_plugin_tortoise_orm-0.1.4.dist-info/licenses/LICENSE
nonebot_plugin_tortoise_orm/__init__.py
nonebot_plugin_tortoise_orm/config.py
nonebot_plugin_tortoise_orm-0.1.4.dist-info/RECORD
