Metadata-Version: 2.1
Name: nonebot-plugin-tortoise-orm
Version: 0.1.4
Summary: 一个通用数据库连接插件
Home-page: https://github.com/kexue-z/nonebot-plugin-tortoise-orm
Author-Email: kexue <xana278@foxmail.com>
License: MIT
Project-URL: Homepage, https://github.com/kexue-z/nonebot-plugin-tortoise-orm
Requires-Python: <4.0,>=3.9
Requires-Dist: nonebot2>=2.0.0
Requires-Dist: nonebot-plugin-localstore>=0.5.0
Requires-Dist: tortoise-orm[asyncmy,asyncodbc,asyncpg]>=0.19.3
Requires-Dist: asyncpg>=0.29.0
Requires-Dist: pyodbc>=5.1.0
Requires-Dist: pyyaml>=6.0.1
